{"info":{"author":"Vova Nenashkin","author_email":"nenashkinvov@gmail.com","bugtrack_url":null,"classifiers":["Development Status :: 3 - Alpha","Intended Audience :: Developers","License :: OSI Approved :: MIT License","Programming Language :: Python :: 3","Topic :: Software Development :: Build Tools"],"description":"","description_content_type":"","docs_url":null,"download_url":"https://github.com/SuLG-ik/Euclid-Algorithm/archive/master.zip","downloads":{"last_day":-1,"last_month":-1,"last_week":-1},"home_page":"https://github.com/SuLG-ik/Euclid-Algorithm","keywords":"SOME,MEANINGFULL,KEYWORDS","license":"MIT","maintainer":"","maintainer_email":"","name":"extended-euclid-integer","package_url":"https://pypi.org/project/extended-euclid-integer/","platform":"","project_url":"https://pypi.org/project/extended-euclid-integer/","project_urls":{"Download":"https://github.com/SuLG-ik/Euclid-Algorithm/archive/master.zip","Homepage":"https://github.com/SuLG-ik/Euclid-Algorithm"},"release_url":"https://pypi.org/project/extended-euclid-integer/0.1/","requires_dist":null,"requires_python":"","summary":"modular inverse","version":"0.1"},"last_serial":6806050,"releases":{"0.1":[{"comment_text":"","digests":{"md5":"10b3aaa03b44398fa69ac9cf295642b2","sha256":"e47241fcd8848f69eb35f786f817287abd2c111a3cf5b44efde8cef752f38252"},"downloads":-1,"filename":"extended_euclid_integer-0.1.tar.gz","has_sig":false,"md5_digest":"10b3aaa03b44398fa69ac9cf295642b2","packagetype":"sdist","python_version":"source","requires_python":null,"size":1348,"upload_time":"2020-03-13T13:33:49","upload_time_iso_8601":"2020-03-13T13:33:49.701094Z","url":"https://files.pythonhosted.org/packages/18/af/bf372819b7491c924a04eb83f1f4e5de84b34c3666c91f6d4106ce2a1fe4/extended_euclid_integer-0.1.tar.gz"}]},"urls":[{"comment_text":"","digests":{"md5":"10b3aaa03b44398fa69ac9cf295642b2","sha256":"e47241fcd8848f69eb35f786f817287abd2c111a3cf5b44efde8cef752f38252"},"downloads":-1,"filename":"extended_euclid_integer-0.1.tar.gz","has_sig":false,"md5_digest":"10b3aaa03b44398fa69ac9cf295642b2","packagetype":"sdist","python_version":"source","requires_python":null,"size":1348,"upload_time":"2020-03-13T13:33:49","upload_time_iso_8601":"2020-03-13T13:33:49.701094Z","url":"https://files.pythonhosted.org/packages/18/af/bf372819b7491c924a04eb83f1f4e5de84b34c3666c91f6d4106ce2a1fe4/extended_euclid_integer-0.1.tar.gz"}]}